trace_events/__init__.py
trace_events/context.py
trace_events/field.py
trace_events/json.py
trace_events/profiler.py
trace_events/timer.py
trace_events/trace.py
trace_events/utils.py
trace_events/events/__init__.py
trace_events/events/complete_event.py
trace_events/events/counter_event.py
trace_events/events/event.py
trace_events-0.1.0.dist-info/LICENSE
trace_events-0.1.0.dist-info/METADATA
trace_events-0.1.0.dist-info/WHEEL
trace_events-0.1.0.dist-info/top_level.txt
trace_events-0.1.0.dist-info/RECORD
