Metadata-Version: 2.1
Name: trace-events
Version: 0.1.0
Summary: Python event tracing using the Trace Event Format supported by Chromium browsers
Home-page: https://github.com/JonathanHiggs/trace_events
Author: Jonathan Higgs
Author-email: jonathan.higgs.11@mail.wbs.ac.uk
License: MIT
Project-URL: Source, https://github.com/JonathanHiggs/trace_events
Project-URL: Bug Tracker, https://github.com/JonathanHiggs/trace_events/issues
Keywords: trace tracing event profile profiler
Classifier: Development Status :: 3 - Alpha
Classifier: Intended Audience :: Developers
Classifier: License :: OSI Approved :: MIT License
Classifier: Natural Language :: English
Classifier: Operating System :: OS Independent
Classifier: Programming Language :: Python :: 3
Classifier: Programming Language :: Python :: 3.8
Classifier: Programming Language :: Python :: 3.9
Classifier: Programming Language :: Python :: 3.10
Classifier: Programming Language :: Python :: 3.11
Classifier: Programming Language :: Python :: 3.12
Classifier: Topic :: Software Development :: Debuggers
Requires-Python: >=3.8
License-File: LICENSE
